{
  "pr_ready": true,
  "output_id": "83b1c00a-52b3-4d0d-a4a7-dd39873280ad",
  "project": "yallaplays",
  "output_type": "seo_page",
  "suggested_branch": "ai/seo_page/83b1c00a",
  "suggested_title": "[AI] SEO Page \u2014 Arabic Games",
  "suggested_description": "SEO-optimised category landing page for Arabic Games on YallaPlays\n\n**Generated by MIFTEH AI OS**\n- Dashboard: https://yallaplays.com/admin/os\n- Output ID: 83b1c00a-52b3-4d0d-a4a7-dd39873280ad\n- AI Generated: False\n- Risk Level: low\n\n**Files Changed:**\n- `src/pages/games/arabic-games/index.tsx`\n- `src/pages/games/arabic-games/seo.ts`",
  "files": [
    {
      "path": "src/pages/games/arabic-games/index.tsx",
      "operation": "create_or_update",
      "description": "SEO-optimised category page for Arabic Games"
    },
    {
      "path": "src/pages/games/arabic-games/seo.ts",
      "operation": "create_or_update",
      "description": "SEO metadata exports for Arabic Games page"
    }
  ],
  "total_files": 2,
  "safety": {
    "rollback_available": true,
    "risk_level": "low",
    "requires_review": true,
    "auto_merge": false
  },
  "generated_at": "2026-05-13T09:20:27.598595"
}